plexutil/__init__.py
plexutil/__main__.py
plexutil/plex_util_logger.py
plexutil/static.py
plexutil/config/log_config.yaml
plexutil/core/__init__.py
plexutil/core/auth.py
plexutil/core/library.py
plexutil/core/library_factory.py
plexutil/core/movie_library.py
plexutil/core/music_library.py
plexutil/core/music_playlist.py
plexutil/core/prompt.py
plexutil/core/tv_library.py
plexutil/dto/__init__.py
plexutil/dto/bootstrap_paths_dto.py
plexutil/dto/dropdown_item_dto.py
plexutil/dto/library_setting_dto.py
plexutil/dto/movie_dto.py
plexutil/dto/music_playlist_dto.py
plexutil/dto/song_dto.py
plexutil/dto/tv_episode_dto.py
plexutil/dto/tv_series_dto.py
plexutil/enums/__init__.py
plexutil/enums/agent.py
plexutil/enums/file_type.py
plexutil/enums/language.py
plexutil/enums/library_setting.py
plexutil/enums/library_type.py
plexutil/enums/scanner.py
plexutil/enums/server_setting.py
plexutil/enums/user_request.py
plexutil/exception/__init__.py
plexutil/exception/auth_error.py
plexutil/exception/bootstrap_error.py
plexutil/exception/database_connection_error.py
plexutil/exception/device_error.py
plexutil/exception/entity_not_found_error.py
plexutil/exception/library_illegal_state_error.py
plexutil/exception/library_op_error.py
plexutil/exception/library_poll_timeout_error.py
plexutil/exception/library_section_missing_error.py
plexutil/exception/library_unsupported_error.py
plexutil/exception/plex_media_missing_error.py
plexutil/exception/unexpected_argument_error.py
plexutil/exception/unexpected_naming_pattern_error.py
plexutil/exception/user_error.py
plexutil/graphical/__init__.py
plexutil/graphical/selection_window.py
plexutil/mapper/__init__.py
plexutil/mapper/music_playlist_mapper.py
plexutil/mapper/song_mapper.py
plexutil/model/__init__.py
plexutil/model/music_playlist_entity.py
plexutil/model/song_entity.py
plexutil/model/song_music_playlist_entity.py
plexutil/service/__init__.py
plexutil/service/db_manager.py
plexutil/service/music_playlist_service.py
plexutil-3.1.3.dist-info/licenses/LICENSE
plexutil-3.1.3.dist-info/METADATA
plexutil-3.1.3.dist-info/WHEEL
plexutil-3.1.3.dist-info/entry_points.txt
plexutil-3.1.3.dist-info/top_level.txt
plexutil-3.1.3.dist-info/RECORD
